ZeroD/__init__.py
ZeroD/receive.py
ZeroD/setupBotWorkspace.py
ZeroD/tasks.py
zerodeg-0.12.1.dist-info/LICENSE
zerodeg-0.12.1.dist-info/METADATA
zerodeg-0.12.1.dist-info/WHEEL
zerodeg-0.12.1.dist-info/top_level.txt
zerodeg-0.12.1.dist-info/RECORD
