Metadata-Version: 2.1
Name: zerodeg
Version: 0.12.1
Summary: 基于OneBot标准的QQ机器人支持库
Home-page: https://gitee.com/tumuidle/zero-d-core
Author: YiLinProject
Author-email: no-reply@idlestudios.top
License: UNKNOWN
Project-URL: Bug Tracker, https://gitee.com/tumuidle/zero-d-core/issues
Platform: UNKNOWN
Classifier: Programming Language :: Python :: 3
Classifier: License :: OSI Approved :: MIT License
Classifier: Operating System :: OS Independent
Requires-Python: >=3.8
License-File: LICENSE
